mcp_b/__init__.py
mcp_b/__main__.py
mcp_b/amum.py
mcp_b/bridge.py
mcp_b/ethic.py
mcp_b/protocol.py
mcp_b/qci.py
mcp_b/workflow.py
mcp_b/templates/bug_fix.yaml
mcp_b/templates/code_review.yaml
mcp_b/templates/default.yaml
mcp_b/templates/feature_planning.yaml
mcp_b-0.3.0.dist-info/METADATA
mcp_b-0.3.0.dist-info/WHEEL
mcp_b-0.3.0.dist-info/entry_points.txt
mcp_b-0.3.0.dist-info/RECORD
