Metadata-Version: 2.4
Name: mcp-b
Version: 0.3.0
Summary: MCP-B (Master Client Bridge) - Connects everything, brings data flow together. Protocol with AMUM-QCI-ETHIC Module
Project-URL: Homepage, https://github.com/bjoernbethge/mcp-b
Project-URL: Documentation, https://github.com/bjoernbethge/mcp-b#readme
Author-email: Björn Bethge <bjoern.bethge@gmail.com>
License-Expression: MIT
Keywords: agentic,agents,amum,bridge,context-engineering,dataflow,duckdb,ethic,master-client-bridge,mcp,mcp-b,multi-agent,protocol,qci,smartace,surrealdb
Classifier: Development Status :: 3 - Alpha
Classifier: Intended Audience :: Developers
Classifier: License :: OSI Approved :: MIT License
Classifier: Programming Language :: Python :: 3
Classifier: Programming Language :: Python :: 3.11
Classifier: Programming Language :: Python :: 3.12
Classifier: Topic :: Scientific/Engineering :: Artificial Intelligence
Requires-Python: >=3.11
Requires-Dist: duckdb>=1.0.0
Requires-Dist: pyyaml>=6.0
Requires-Dist: surrealdb>=0.3.0
Provides-Extra: dev
Requires-Dist: black; extra == 'dev'
Requires-Dist: pytest>=7.0; extra == 'dev'
Requires-Dist: ruff; extra == 'dev'
Provides-Extra: full
Requires-Dist: numpy>=1.24.0; extra == 'full'
